tigerpy_drawing.py
tigerpy_drawing-1.0.0.dist-info/licenses/LICENSE
tigerpy_drawing-1.0.0.dist-info/METADATA
tigerpy_drawing-1.0.0.dist-info/WHEEL
tigerpy_drawing-1.0.0.dist-info/top_level.txt
tigerpy_drawing-1.0.0.dist-info/RECORD
