Metadata-Version: 2.4
Name: tigerpy_drawing
Version: 1.0.0
Summary: Tigerpy Drawing Python Library
Author-email: Pradeep Yadav <tigerpydev@gmail.com>
License: MIT License
Keywords: svg,drawing,canvas
Requires-Python: >=3.8
License-File: LICENSE
Dynamic: license-file
